vsn800_ardexa.py
vsn800_ardexa-1.3.1.dist-info/DESCRIPTION.rst
vsn800_ardexa-1.3.1.dist-info/METADATA
vsn800_ardexa-1.3.1.dist-info/RECORD
vsn800_ardexa-1.3.1.dist-info/WHEEL
vsn800_ardexa-1.3.1.dist-info/entry_points.txt
vsn800_ardexa-1.3.1.dist-info/metadata.json
vsn800_ardexa-1.3.1.dist-info/top_level.txt
