Metadata-Version: 2.0
Name: vsn800-ardexa
Version: 1.3.1
Summary: Collect from Phoenix Contact SOLARCHECK String Monitor and send the data to your cloud using Ardexa
Home-page: https://github.com/ardexa/vsn800-weather
Author: Ardexa Pty Limited
Author-email: support@ardexa.com
License: UNKNOWN
Project-URL: Source, https://github.com/ardexa/vsn800-weather/
Project-URL: Bug Reports, https://github.com/ardexa/vsn800-weather/issues
Keywords: ABB VSN800 weather station solar ardexa
Platform: UNKNOWN
Classifier: License :: OSI Approved :: MIT License
Classifier: Programming Language :: Python :: 2
Classifier: Programming Language :: Python :: 2.7
Classifier: Programming Language :: Python :: 3
Classifier: Programming Language :: Python :: 3.4
Classifier: Programming Language :: Python :: 3.5
Classifier: Programming Language :: Python :: 3.6
Requires-Python: >=2.7
Requires-Dist: future
Requires-Dist: ardexaplugin
Requires-Dist: Click
